setup.py
conduit/__init__.py
conduit/base.py
conduit/exceptions.py
conduit/models.py
conduit/subscribe.py
conduit/api/__init__.py
conduit/api/base.py
conduit/api/fields.py
conduit/api/utils.py
conduit/management/__init__.py
conduit/management/commands/__init__.py
conduit/management/commands/create_api.py
conduit/management/commands/run_api_server.py
conduit/test/__init__.py
conduit/test/conduit_formats.py
conduit/test/test_custom_pkfield_overrides.py
conduit/test/test_modelresource_conduit_formats.py
conduit/test/test_modelresource_methods.py
conduit/test/testcases.py
django_conduit.egg-info/PKG-INFO
django_conduit.egg-info/SOURCES.txt
django_conduit.egg-info/dependency_links.txt
django_conduit.egg-info/not-zip-safe
django_conduit.egg-info/requires.txt
django_conduit.egg-info/top_level.txt