Metadata-Version: 1.1
Name: django-conduit
Version: 0.1.1
Summary: Easy and powerful REST APIs for Django.
Home-page: https://github.com/akoumjian/django-conduit
Author: Alec Koumjian
Author-email: akoumjian@gmail.com
License: Apache 2.0
Platform: UNKNOWN
Classifier: Development Status :: 4 - Beta
Classifier: Environment :: Web Environment
Classifier: Framework :: Django
Classifier: Intended Audience :: Developers
Classifier: License :: OSI Approved :: BSD License
Classifier: Operating System :: OS Independent
Classifier: Programming Language :: Python
Classifier: Topic :: Utilities
